rtl/fsm_ctrl.v
module fsm_ctrl (
    input wire clk,
    input wire rst_n,
    input wire stream,
    output reg match
);

parameter state0 = 3'b000; //start
parameter state1 = 3'b001; //1
parameter state2 = 3'b010; //10
parameter state3 = 3'b011; //101
parameter state4 = 3'b100; //1011

parameter MEALY_FSM = 1;

reg [2:0] state_reg, state_next;

always @(posedge clk or negedge rst_n) begin
    if (!rst_n) begin
        state_reg <= state0;
    end else begin
        state_reg <= state_next;
    end
end

always @(*) begin
    state_next = state_reg;
    case (state_reg)
        state0: begin
            if (stream == 0) 
                state_next = state0;
            else
                state_next = state1;
        end

        state1: begin
            if (stream == 0) 
                state_next = state2;
            else
                state_next = state1;
        end

        state2: begin
            if (stream == 0) 
                state_next = state0;
            else
                state_next = state3;
        end

        state3: begin
            if (stream == 0)
                state_next = state0;
            else 
                state_next = state4;
        end

        state4: begin
            if (stream == 0) 
                state_next = state2;
            else
                state_next = state1;
        end
    endcase
end

generate 
    if (MEALY_FSM) begin 
        always @(*) begin
            case (state_reg)
                state0: match = 0;
                state1: match = 0;
                state2: match = 0;
                state3: begin
                    if (stream) 
                        match = 1;
                    else
                        match = 0;
                end
                state4: match = 0;
                default: match = 0;
            endcase
        end
    end else begin
        always @(*) begin
            match = (state_reg == state4);
        end
    end
endgenerate

endmodule

dv/fsm_ctrl_tb.v
module fsm_ctrl_tb;

	`ifdef MEALY_FSM
        	parameter MEALY_FSM = `MEALY_FSM;
    	`else
        	parameter MEALY_FSM = 1'b0;
    	`endif

    	`ifdef LENGTH
        	parameter LENGTH = `LENGTH;
    	`else
        	parameter LENGTH = 32;
    	`endif

	reg clk, rst_n;
	reg stream;

	wire match;
	
	integer i;

fsm_ctrl #(.MEALY_FSM(MEALY_FSM)) u_dut (.clk(clk), .rst_n(rst_n), .stream(stream), .match(match));

initial begin
	$dumpfile ("fsm_ctrl_wave.vcd");
	$dumpvars (0, fsm_ctrl_tb);
	clk = 0;
	forever #1 clk = ~clk;
end

initial begin
	rst_n = 0;

	#1;
	rst_n = 1; 
	stream = 0;

	#1;
	for (i = 0; i < LENGTH; i = i + 1) begin
		@(posedge clk);
		stream = $random;
		#1;
		$display ("stream = %b, match = %b", stream, match);
	end

	#50;
	$finish;
end

endmodule

sim/fsm_ctrl_wave.vcd
$date
	Sun Sep 15 16:21:39 2024
$end
$version
	Icarus Verilog
$end
$timescale
	1s
$end
$scope module fsm_ctrl_tb $end
$var wire 1 ! match $end
$var parameter 32 " LENGTH $end
$var parameter 32 # MEALY_FSM $end
$var reg 1 $ clk $end
$var reg 1 % rst_n $end
$var reg 1 & stream $end
$var integer 32 ' i [31:0] $end
$scope module u_dut $end
$var wire 1 $ clk $end
$var wire 1 % rst_n $end
$var wire 1 & stream $end
$var parameter 32 ( MEALY_FSM $end
$var parameter 3 ) state0 $end
$var parameter 3 * state1 $end
$var parameter 3 + state2 $end
$var parameter 3 , state3 $end
$var parameter 3 - state4 $end
$var reg 1 ! match $end
$var reg 3 . state_next [2:0] $end
$var reg 3 / state_reg [2:0] $end
$scope begin genblk1 $end
$upscope $end
$upscope $end
$upscope $end
$enddefinitions $end
$comment Show the parameter values. $end
$dumpall
b100 -
b11 ,
b10 +
b1 *
b0 )
b1 (
b1 #
b100000 "
$end
#0
$dumpvars
b0 /
b1 .
bx '
x&
0%
0$
0!
$end
#1
b1 /
b10 .
0&
1%
1$
#2
b0 '
0$
#3
b0 .
b10 /
1$
#4
b1 '
0$
#5
b0 /
b1 .
1&
1$
#6
b10 '
0$
#7
b1 /
1$
#8
b11 '
0$
#9
1$
#10
b100 '
0$
#11
1$
#12
b101 '
0$
#13
1$
#14
b110 '
0$
#15
1$
#16
b111 '
0$
#17
b10 .
0&
1$
#18
b1000 '
0$
#19
b10 /
b11 .
1&
1$
#20
b1001 '
0$
#21
b100 .
1!
b11 /
1$
#22
b1010 '
0$
#23
b100 /
0!
b10 .
0&
1$
#24
b1011 '
0$
#25
b10 /
b11 .
1&
1$
#26
b1100 '
0$
#27
1!
b100 .
b11 /
1$
#28
b1101 '
0$
#29
b100 /
b10 .
0!
0&
1$
#30
b1110 '
0$
#31
b10 /
b11 .
1&
1$
#32
b1111 '
0$
#33
b11 /
b0 .
0&
1$
#34
b10000 '
0$
#35
b0 /
b1 .
0!
1&
1$
#36
b10001 '
0$
#37
b1 /
b10 .
0&
1$
#38
b10010 '
0$
#39
b10 /
b11 .
1&
1$
#40
b10011 '
0$
#41
b100 .
1!
b11 /
1$
#42
b10100 '
0$
#43
b100 /
0!
b10 .
0&
1$
#44
b10101 '
0$
#45
b10 /
b11 .
1&
1$
#46
b10110 '
0$
#47
b11 /
b0 .
0&
1$
#48
b10111 '
0$
#49
b0 /
1$
#50
b11000 '
0$
#51
1$
#52
b11001 '
0$
#53
b1 .
1&
1$
#54
b11010 '
0$
#55
b1 /
b10 .
0&
1$
#56
b11011 '
0$
#57
b10 /
b11 .
1&
1$
#58
b11100 '
0$
#59
1!
b100 .
b11 /
1$
#60
b11101 '
0$
#61
b1 .
0!
b100 /
1$
#62
b11110 '
0$
#63
b1 /
1$
#64
b11111 '
0$
#65
b10 .
0&
1$
#66
b100000 '
0$
#67
b0 .
b10 /
1$
#68
0$
#69
b0 /
1$
